LICENSE
MANIFEST.in
Makefile
README.md
setup.cfg
setup.py
bin/kforce
kforce/__init__.py
kforce/aws_facts.py
kforce/cache.py
kforce/commands.py
kforce/pre_steps.py
kforce/utils.py
kforce.egg-info/PKG-INFO
kforce.egg-info/SOURCES.txt
kforce.egg-info/dependency_links.txt
kforce.egg-info/requires.txt
kforce.egg-info/top_level.txt
kforce/raw_templates/cluster.yaml
kforce/raw_templates/values.yaml.j2
kforce/raw_templates/snippets/gpu.yaml
requirements/base.txt
requirements/dev.txt
tests/__init__.py
tests/__pycache__/__init__.cpython-36.pyc
tests/integration/__init__.py
tests/integration/test_commands.py
tests/integration/__pycache__/__init__.cpython-36.pyc
tests/integration/__pycache__/test_commands.cpython-36-PYTEST.pyc
tests/unit/test_aws_facts.py
tests/unit/test_commands.py
tests/unit/test_pre_steps.py
tests/unit/test_renderer.py
tests/unit/test_utils.py
tests/unit/__pycache__/test_aws_facts.cpython-36-PYTEST.pyc
tests/unit/__pycache__/test_command.cpython-36-PYTEST.pyc
tests/unit/__pycache__/test_commands.cpython-36-PYTEST.pyc
tests/unit/__pycache__/test_pre_steps.cpython-36-PYTEST.pyc
tests/unit/__pycache__/test_renderer.cpython-36-PYTEST.pyc
tests/unit/__pycache__/test_utils.cpython-36-PYTEST.pyc