Metadata-Version: 1.0
Name: kforce
Version: 0.1.25
Summary: KOPS template automation
Home-page: https://github.com/ycliuhw/kforce
Author: Yang Kelvin Liu
Author-email: ycliuhw@gmail.com
License: Apache License 2.0
Keywords: k8s,kops,kubernetes,template
Platform: UNKNOWN
